mcfonts/__init__.py
mcfonts/__main__.py
mcfonts/compacting.py
mcfonts/constants.py
mcfonts/coverage_reports.py
mcfonts/exceptions.py
mcfonts/export_formats.py
mcfonts/filters.py
mcfonts/glyphs.py
mcfonts/providers/base.py
mcfonts/providers/bitmap.py
mcfonts/providers/legacy_unicode.py
mcfonts/providers/reference.py
mcfonts/providers/space.py
mcfonts/providers/ttf.py
mcfonts/providers/unihex.py
mcfonts/utils/colors.py
mcfonts/utils/image.py
mcfonts/utils/importing.py
mcfonts/utils/resources.py
mcfonts/utils/schemas.py
mcfonts/utils/types.py
mcfonts/utils/unicode.py
mcfonts/utils/unihex.py
mcfonts/utils/exporting/opentype.py
mcfonts/utils/exporting/unihex.py
mcfonts/utils/exporting/yaff.py
mcfonts-0.7.dist-info/LICENSE.txt
mcfonts-0.7.dist-info/METADATA
mcfonts-0.7.dist-info/WHEEL
mcfonts-0.7.dist-info/top_level.txt
mcfonts-0.7.dist-info/RECORD
