Metadata-Version: 2.1
Name: mcfonts
Version: 0.7
Summary: A module for exporting, manipulating, and working with Minecraft fonts
Author: WhoAteMyButter
License: MIT
Project-URL: Documentation, https://mcfonts.readthedocs.io
Project-URL: Source, https://gitlab.com/whoatemybutter/mcfonts
Project-URL: Changelog, https://gitlab.com/whoatemybutter/mcfonts/-/blob/master/CHANGELOG.md
Project-URL: Issues, https://gitlab.com/whoatemybutter/mcfonts/-/issues
Keywords: minecraft,fonts,minecraft fonts,font exporting,minecraft opentype,minecraft font,minecraft export font,mc font,mc fonts,mcfonts
Classifier: Programming Language :: Python :: 3
Classifier: Programming Language :: Python :: 3 :: Only
Classifier: Programming Language :: Python :: 3.11
Classifier: Operating System :: OS Independent
Classifier: Topic :: Games/Entertainment
Classifier: Topic :: Text Processing :: Fonts
Classifier: Topic :: Utilities
Classifier: Typing :: Typed
Classifier: Development Status :: 3 - Alpha
Classifier: Intended Audience :: End Users/Desktop
Classifier: Intended Audience :: Other Audience
Classifier: Intended Audience :: Developers
Classifier: License :: OSI Approved :: MIT License
Classifier: Natural Language :: English
Requires-Python: >=3.11
License-File: LICENSE.txt
Requires-Dist: fontTools >=4.35.0
Requires-Dist: Pillow >=9.3.0
Requires-Dist: lxml >=4.9.0
Requires-Dist: tinyunicodeblock >=1.1.0
Requires-Dist: jsonschema >=4.17.3
Requires-Dist: unirange >=1.0
Provides-Extra: docs
Requires-Dist: Sphinx >=5.3.0 ; extra == 'docs'
Requires-Dist: sphinx-autoapi >=2.0.0 ; extra == 'docs'
Requires-Dist: sphinxext-opengraph >=0.8.2 ; extra == 'docs'
Requires-Dist: sphinx-immaterial >=0.11.3 ; extra == 'docs'
